ge/__init__.py
ge/alias.py
ge/classify.py
ge/utils.py
ge/walker.py
ge/cluster/__init__.py
ge/cluster/cluster.py
ge/evaluation/__init__.py
ge/evaluation/tool.py
ge/geotool/__init__.py
ge/geotool/geoangle.py
ge/geotool/geofigures.py
ge/geotool/geoplot.py
ge/geotool/vec2anglemarmid.py
ge/models/__init__.py
ge/models/deepwalk.py
ge/models/line.py
ge/models/node2vec.py
ge/models/sdne.py
ge/models/struc2vec.py
ge/models/struc2vec1.py
ge/models/struc2vec2.py
geonet-0.0.1.dist-info/LICENSE
geonet-0.0.1.dist-info/METADATA
geonet-0.0.1.dist-info/WHEEL
geonet-0.0.1.dist-info/top_level.txt
geonet-0.0.1.dist-info/RECORD
