Metadata-Version: 2.1
Name: geonet
Version: 0.0.1
Home-page: https://github.com/xxx
Author: Sure Wong
Author-email: surewongcom@gmail.com
License: GPL license
Requires-Python: >=3.4
License-File: LICENSE
Requires-Dist: gensim (==3.6.0)
Requires-Dist: networkx (==2.1)
Requires-Dist: joblib (==0.13.0)
Requires-Dist: fastdtw (==0.3.2)
Requires-Dist: tqdm
Requires-Dist: numpy
Requires-Dist: scikit-learn
Requires-Dist: pandas
Requires-Dist: matplotlib
Provides-Extra: cpu
Requires-Dist: tensorflow (!=1.7.*,!=1.8.*,>=1.4.0) ; extra == 'cpu'
Provides-Extra: gpu
Requires-Dist: tensorflow-gpu (!=1.7.*,!=1.8.*,>=1.4.0) ; extra == 'gpu'
